facefilters/__init__.py
facefilters/main.py
facefilters/utils.py
navimagefilters-0.0.1.dist-info/METADATA
navimagefilters-0.0.1.dist-info/WHEEL
navimagefilters-0.0.1.dist-info/top_level.txt
navimagefilters-0.0.1.dist-info/RECORD
