Metadata-Version: 2.1
Name: navimagefilters
Version: 0.0.1
Summary: UNKNOWN
Home-page: https://github.com/Navaneeth-Sharma/imagefilters/
Author: Navaneeth
Author-email: navaneethsharma2310oct@gmail.com
License: UNKNOWN
Platform: UNKNOWN
Classifier: Programming Language :: Python :: 3
Classifier: License :: OSI Approved :: MIT License
Classifier: Operating System :: OS Independent
Requires-Python: >=3.6
